wbsurfer/__init__.py
wbsurfer/_version.py
wbsurfer/border.py
wbsurfer/cli.py
wbsurfer/geodesic.py
wbsurfer/logging.py
wbsurfer/movie.py
wbsurfer/scene.py
wbsurfer/utils.py
wbsurfer/volume.py
wbsurfer2-0.3.0.dist-info/licenses/LICENSE
wbsurfer2-0.3.0.dist-info/METADATA
wbsurfer2-0.3.0.dist-info/WHEEL
wbsurfer2-0.3.0.dist-info/entry_points.txt
wbsurfer2-0.3.0.dist-info/top_level.txt
wbsurfer2-0.3.0.dist-info/zip-safe
wbsurfer2-0.3.0.dist-info/RECORD
