Metadata-Version: 2.4
Name: wbsurfer2
Version: 0.3.0
Summary: CLI tool for making CIFTI-related movies
Author-email: Andrew Van <vanandrew77@gmail.com>
License: MIT License
Project-URL: github, https://github.com/vanandrew/wbsurfer2
Keywords: neuroimaging
Classifier: License :: OSI Approved :: MIT License
Requires-Python: >=3.10
License-File: LICENSE
Requires-Dist: geodesic-chenhan>=0.1.1
Requires-Dist: networkx>=3.4.1
Requires-Dist: nibabel>=5.3.0
Requires-Dist: rich>=13.9.3
Requires-Dist: scipy>=1.14.1
Requires-Dist: trimesh>=4.4.9
Dynamic: license-file
